_bloock_bridge_lib.abi3.so
bloock-2.9.8.dist-info/METADATA
bloock-2.9.8.dist-info/top_level.txt
bloock-2.9.8.dist-info/WHEEL
bloock-2.9.8.dist-info/RECORD
bloock/__init__.py
bloock/py.typed
bloock/_ffi/build.py
bloock/_ffi/__init__.py
bloock/_ffi/ffi.py
bloock/client/availability.py
bloock/client/encryption.py
bloock/client/identity.py
bloock/client/identity_core.py
bloock/client/webhook.py
bloock/client/__init__.py
bloock/client/authenticity.py
bloock/client/integrity.py
bloock/client/key.py
bloock/client/record.py
bloock/_config/__init__.py
bloock/_config/config.py
bloock/entity/__init__.py
bloock/entity/encryption/encryption_alg.py
bloock/entity/encryption/__init__.py
bloock/entity/encryption/encrypter.py
bloock/entity/authenticity/signer.py
bloock/entity/authenticity/signature_alg.py
bloock/entity/authenticity/signature_header_jws.py
bloock/entity/authenticity/signature.py
bloock/entity/authenticity/__init__.py
bloock/entity/authenticity/signature_jws.py
bloock/entity/authenticity/hash_alg.py
bloock/entity/integrity/__init__.py
bloock/entity/integrity/record_receipt.py
bloock/entity/integrity/anchor.py
bloock/entity/integrity/network.py
bloock/entity/integrity/proof_anchor.py
bloock/entity/integrity/anchor_network.py
bloock/entity/integrity/proof.py
bloock/entity/identity/decimal_attribute.py
bloock/entity/identity/issuer.py
bloock/entity/identity/schema.py
bloock/entity/identity/string_attribute_descriptor.py
bloock/entity/identity/credential_receipt.py
bloock/entity/identity/date_attribute.py
bloock/entity/identity/did.py
bloock/entity/identity/credential_proof.py
bloock/entity/identity/integer_attribute.py
bloock/entity/identity/verification_receipt.py
bloock/entity/identity/schema_builder.py
bloock/entity/identity/__init__.py
bloock/entity/identity/integer_enum_attribute_descriptor.py
bloock/entity/identity/credential_status.py
bloock/entity/identity/issuer_state_receipt.py
bloock/entity/identity/string_attribute.py
bloock/entity/identity/decimal_enum_attribute_descriptor.py
