Metadata-Version: 2.1
Name: bloock
Version: 2.9.8
Summary: Bloock library for Python
Author: Bloock
Classifier: Development Status :: 5 - Production/Stable
Classifier: Programming Language :: Python :: 3.7
Classifier: License :: OSI Approved :: Apache Software License
Requires-Python: >=3.7
Requires-Dist: cffi ~=1.15
Requires-Dist: grpcio >=1.49.1
Requires-Dist: protobuf <5.0dev,>=4.21.3
